[
  {
    "tag": "couple",
    "src": "https://drive.google.com/uc?export=view&id=1JLbkaYhIOefFgMYwt00h4w1pKa7EVKbn"
  },
  {
    "tag": "couple",
    "src": "https://drive.google.com/uc?export=view&id=1O8VpE1Pjac1dIqn7e_Gzx02Lo4JXg_7Z"
  },
  {
    "tag": "couple",
    "src": "https://drive.google.com/uc?export=view&id=1qfJdSKGW1Gc25vZgLLqzPM3L6nicjPgP"
  },
  {
    "tag": "couple",
    "src": "https://drive.google.com/uc?export=view&id=1nTJ76dJ4eBwSDpK1M8Ev_t7LXFXjY7dv"
  },
  {
    "tag": "couple",
    "src": "https://drive.google.com/uc?export=view&id=1IRGr78FN3Kgzgz0r-xlzrfWWAjkGx36c"
  },
  {
    "tag": "couple",
    "src": "https://drive.google.com/uc?export=view&id=1CGX5DpzYGs0C8KoedqAO8W_ew2Y5eiqg"
  },
  {
    "tag": "couple",
    "src": "https://drive.google.com/uc?export=view&id=1cxLhVelLDptMxaKeZsNnrABGkoY_O4h1"
  },
  {
    "tag": "couple",
    "src": "https://drive.google.com/uc?export=view&id=1GuYtWqRzN-oA4gPEyylXiX2i7reygbXW"
  },
  {
    "tag": "couple",
    "src": "https://drive.google.com/uc?export=view&id=1_a3LpOTP-PLbIkWITRin_fV414VnyVmO"
  },
  {
    "tag": "couple",
    "src": "https://drive.google.com/uc?export=view&id=1PzxIr01E4Ie8ndlAYAo360Zdf6454Ads"
  },
  {
    "tag": "couple",
    "src": "https://drive.google.com/uc?export=view&id=1b33CeqoQyOdp21LjCpAuqs_ZxhNJRrCG"
  },
  {
    "tag": "couple",
    "src": "https://drive.google.com/uc?export=view&id=1IPUcq8M86gJmdzaq4CdKismoFepI7xnn"
  },
  {
    "tag": "couple",
    "src": "https://drive.google.com/uc?export=view&id=1wWgCs7U7RsAFCoMU-7iRNr8JYxR_3VeP"
  },
  {
    "tag": "couple",
    "src": "https://drive.google.com/uc?export=view&id=1OLLxoW6L8X6ry25xiZiSAPnqwXa2v93d"
  },
  {
    "tag": "couple",
    "src": "https://drive.google.com/uc?export=view&id=1Z2pKm2-hAz3FEQrv-2_6MlvrcA82jOxe"
  },
  {
    "tag": "couple",
    "src": "https://drive.google.com/uc?export=view&id=1v-L6e9_9uEfrNoY4hbiiBIxt8fDAw3u5"
  },
  {
    "tag": "couple",
    "src": "https://drive.google.com/uc?export=view&id=1HqmgGNrrbEMwB9dMKWweHmIvK-rc-wJx"
  },
  {
    "tag": "couple",
    "src": "https://drive.google.com/uc?export=view&id=1QNBTazcWxIEVyfAXsZkDBfuI24rlsn7I"
  },
  {
    "tag": "couple",
    "src": "https://drive.google.com/uc?export=view&id=1_Z7UJofk1kyjBC7_rziUX1eG_UiXqyVU"
  },
  {
    "tag": "couple",
    "src": "https://drive.google.com/uc?export=view&id=1khf6gRlexZAtB-Xp1NGm75VVAYDrK8Qc"
  },
  {
    "tag": "couple",
    "src": "https://drive.google.com/uc?export=view&id=1uTgSasdlwrK_G8Y_-JBkg3yZLI7MhtQy"
  },
  {
    "tag": "couple",
    "src": "https://drive.google.com/uc?export=view&id=1CeXOWbuP8B7IDUliX8qbtFSKBfZs8HUJ"
  },
  {
    "tag": "portrait",
    "src": "https://drive.google.com/uc?export=view&id=1Ow6pgLQtfElESB62u5vo8KbbRC05Nbjs"
  },
  {
    "tag": "portrait",
    "src": "https://drive.google.com/uc?export=view&id=1eYUo-m3ttBumOLPKGdiGzWOSLHbn82Is"
  },
  {
    "tag": "portrait",
    "src": "https://drive.google.com/uc?export=view&id=1xtZlyV6-lvGIuXFhPUGjgQWj2QORBT_-"
  },
  {
    "tag": "portrait",
    "src": "https://drive.google.com/uc?export=view&id=1ayq8BeGq6ZrEgWusVjR7quq8HkITQfog"
  },
  {
    "tag": "portrait",
    "src": "https://drive.google.com/uc?export=view&id=1rFx4wM_zUIhqtj5b1745UZWWSgysGC3d"
  },
  {
    "tag": "portrait",
    "src": "https://drive.google.com/uc?export=view&id=1kK1HWet41CU7gmF2SGXo16c6kvnFyVKp"
  },
  {
    "tag": "portrait",
    "src": "https://drive.google.com/uc?export=view&id=1mOdMKlPJxxmV7QGl1JM_UcK5SUQCUJbe"
  },
  {
    "tag": "portrait",
    "src": "https://drive.google.com/uc?export=view&id=1JYIgT7tDwzKUdUawUIGWBOwGMYBolUNe"
  },
  {
    "tag": "portrait",
    "src": "https://drive.google.com/uc?export=view&id=1zjYendV6GfxoycZ6kmfbbGLzQELPh9Ty"
  },
  {
    "tag": "portrait",
    "src": "https://drive.google.com/uc?export=view&id=1lbCwUW8YxGfAF0FPekOMNP83sCy1ivEV"
  },
  {
    "tag": "portrait",
    "src": "https://drive.google.com/uc?export=view&id=1X0o2FqEgSKtjbJ791DVTWjan_15iKtsO"
  },
  {
    "tag": "portrait",
    "src": "https://drive.google.com/uc?export=view&id=16xy4pvpGbKeXVmdEguC8heFHFVFueMt2"
  },
  {
    "tag": "portrait",
    "src": "https://drive.google.com/uc?export=view&id=1D7J_-BeHvkIh0cAAqxYmfepcXIdrMj3x"
  },
  {
    "tag": "portrait",
    "src": "https://drive.google.com/uc?export=view&id=1BASv8c_-4Is0et-mjhyu3N_3u0VExo3c"
  },
  {
    "tag": "portrait",
    "src": "https://drive.google.com/uc?export=view&id=13W35gEh4Kc-0xUYk8JpiMntLx_4fySXu"
  },
  {
    "tag": "portrait",
    "src": "https://drive.google.com/uc?export=view&id=1CZjGQYgiPjaQk5aQeiZdr_0HSdMWmchj"
  },
  {
    "tag": "portrait",
    "src": "https://drive.google.com/uc?export=view&id=1CNwacjopUeApQOEvfccbfoqIybBfeQcN"
  },
  {
    "tag": "portrait",
    "src": "https://drive.google.com/uc?export=view&id=1bK0gWbyVsWBuaa5gGuX6fJoPJzRB6C6l"
  },
  {
    "tag": "portrait",
    "src": "https://drive.google.com/uc?export=view&id=1OEnmmjtBU6D4J6OMedi_J8YhMgpGumtP"
  },
  {
    "tag": "portrait",
    "src": "https://drive.google.com/uc?export=view&id=1vkF9jO6EhCCY2LMhPJhmo1df8xS-6SiZ"
  },
  {
    "tag": "portrait",
    "src": "https://drive.google.com/uc?export=view&id=1Zuq7i8rwYH7zl0thNJClg8XT5e34Cr2t"
  },
  {
    "tag": "portrait",
    "src": "https://drive.google.com/uc?export=view&id=1wu70HaVri6ejivWUTNuRD9n8rWH259sh"
  },
  {
    "tag": "portrait",
    "src": "https://drive.google.com/uc?export=view&id=1FeHKcKV7wngiXrPd34ROWxwTiNdA0wp9"
  },
  {
    "tag": "portrait",
    "src": "https://drive.google.com/uc?export=view&id=1BSN_K21DSmPrLhL6TPgH1HC-T6L8ymOl"
  },
  {
    "tag": "portrait",
    "src": "https://drive.google.com/uc?export=view&id=11kHqx_0OaV3C50OTw9ILydr1nEgNgZqA"
  },
  {
    "tag": "portrait",
    "src": "https://drive.google.com/uc?export=view&id=1EH7o8gBduH3YvfFVhhX-nu0eg2LqhjVa"
  },
  {
    "tag": "portrait",
    "src": "https://drive.google.com/uc?export=view&id=1VjeC4h0p1CwxA9EK_2jO5fhTYtK7xyl4"
  },
  {
    "tag": "portrait",
    "src": "https://drive.google.com/uc?export=view&id=1RW_brp2pcgc-XbJHJ2Vrb5jPEWW73S3x"
  },
  {
    "tag": "portrait",
    "src": "https://drive.google.com/uc?export=view&id=1ykYW781-82irGUKJaqLuwsoY1KGkCIes"
  },
  {
    "tag": "portrait",
    "src": "https://drive.google.com/uc?export=view&id=1gDHgkMimpZdC3mPCr5JazWPQPz3Km4lL"
  },
  {
    "tag": "portrait",
    "src": "https://drive.google.com/uc?export=view&id=1LnCftdmEtucw3VaXs_ARACHPC7fPZSS8"
  },
  {
    "tag": "portrait",
    "src": "https://drive.google.com/uc?export=view&id=1BfRyJvrINMvm8soEzeuYojhOlGQfK2q7"
  },
  {
    "tag": "portrait",
    "src": "https://drive.google.com/uc?export=view&id=1iHy_h9_hi_dsXux8XtBGY8P_RD4SjKul"
  },
  {
    "tag": "engagement",
    "src": "https://drive.google.com/uc?export=view&id=1FGkebuBwmqyFKM6ZoCpZJUeZQN7UfPHV"
  },
  {
    "tag": "engagement",
    "src": "https://drive.google.com/uc?export=view&id=1mijAzcNXCFu9XlHc7BgTpuyaH7q5Ua7v"
  },
  {
    "tag": "engagement",
    "src": "https://drive.google.com/uc?export=view&id=1DEYclOtF_GjYecg4Gbrkbbj30ATdIBnG"
  },
  {
    "tag": "engagement",
    "src": "https://drive.google.com/uc?export=view&id=1NYWqHBvP9wyWKHs0-ebGJAqEAMl-SJfQ"
  },
  {
    "tag": "engagement",
    "src": "https://drive.google.com/uc?export=view&id=1f3iJ_SRqIm_vYUMpn3DgHi68yj4nuqvD"
  },
  {
    "tag": "engagement",
    "src": "https://drive.google.com/uc?export=view&id=18DYEIlTxjYJPeHirlqcXMtR2TxKbS8b-"
  },
  {
    "tag": "family",
    "src": "https://drive.google.com/uc?export=view&id=1Wo5v5I2PyVFtMTcq1q-OG90gQL1F32rl"
  },
  {
    "tag": "family",
    "src": "https://drive.google.com/uc?export=view&id=1HaZZIGFUCX-v2F3DdKHN6X0EThhRPFQj"
  },
  {
    "tag": "maternity",
    "src": "https://drive.google.com/uc?export=view&id=1VSPHhpDIzuArya9jBAxuoqMoED4Gry77"
  },
  {
    "tag": "maternity",
    "src": "https://drive.google.com/uc?export=view&id=18unyh4Q4srG252v1J6smDteAmfuwzRd9"
  },
  {
    "tag": "maternity",
    "src": "https://drive.google.com/uc?export=view&id=1J-t_QIIoNe-sON05BekVcVsGXuS43_66"
  },
  {
    "tag": "maternity",
    "src": "https://drive.google.com/uc?export=view&id=1qHpDX1XlYXBi-eRiUSP554J_8wZWbpVi"
  },
  {
    "tag": "maternity",
    "src": "https://drive.google.com/uc?export=view&id=1IJE9sxozLFeFn8OZTGJNZs7kasEEKC0N"
  },
  {
    "tag": "maternity",
    "src": "https://drive.google.com/uc?export=view&id=13k7JRf2xN0GgIXj2gH9DN-B1jgKpaSiO"
  },
  {
    "tag": "maternity",
    "src": "https://drive.google.com/uc?export=view&id=1XcYJL-LkppoyELsYwNBo1B66JHBMsnLr"
  },
  {
    "tag": "maternity",
    "src": "https://drive.google.com/uc?export=view&id=1kI6xGhVTjW7PiDGGs7Iye1uIsfEWqmWW"
  }
]
